pyannotators_keybert/__init__.py
pyannotators_keybert/keybert.py
pyannotators_keybert-0.4.0.dist-info/entry_points.txt
pyannotators_keybert-0.4.0.dist-info/WHEEL
pyannotators_keybert-0.4.0.dist-info/METADATA
pyannotators_keybert-0.4.0.dist-info/RECORD
