Metadata-Version: 2.1
Name: pyannotators-keybert
Version: 0.4.0
Summary: Annotator based on Huggingface transformers zero-shot classification pipeline
Home-page: https://github.com/oterrier/pyannotators_keybert/
Keywords: 
Author: Olivier Terrier
Author-email: olivier.terrier@kairntech.com
Requires-Python: >=3.8
Classifier: Intended Audience :: Information Technology
Classifier: Intended Audience :: Developers
Classifier: Intended Audience :: System Administrators
Classifier: Operating System :: OS Independent
Classifier: Topic :: Software Development :: Libraries :: Application Frameworks
Classifier: Topic :: Software Development :: Libraries :: Python Modules
Classifier: Topic :: Software Development :: Libraries
Classifier: Topic :: Software Development
Classifier: License :: OSI Approved :: MIT License
Classifier: Development Status :: 4 - Beta
Classifier: Programming Language :: Python :: 3.8
Requires-Dist: pymultirole-plugins>=0.4.0,<0.5.0
Requires-Dist: torch==1.7.1
Requires-Dist: keybert
Requires-Dist: scikit-learn==0.23.2
Requires-Dist: stopwordsiso
Requires-Dist: PyICU
Requires-Dist: flit ; extra == "dev"
Requires-Dist: pre-commit ; extra == "dev"
Requires-Dist: bump2version ; extra == "dev"
Requires-Dist: sphinx ; extra == "docs"
Requires-Dist: sphinx-rtd-theme ; extra == "docs"
Requires-Dist: m2r2 ; extra == "docs"
Requires-Dist: sphinxcontrib.apidoc ; extra == "docs"
Requires-Dist: jupyter_sphinx ; extra == "docs"
Requires-Dist: pytest ; extra == "test"
Requires-Dist: pytest-cov ; extra == "test"
Requires-Dist: pytest-flake8 ; extra == "test"
Requires-Dist: pytest-black ; extra == "test"
Requires-Dist: hypothesis ; extra == "test"
Requires-Dist: tox ; extra == "test"
Provides-Extra: dev
Provides-Extra: docs
Provides-Extra: test
